aioboot/__init__.py
aioboot/app.py
aioboot/application.py
aioboot/cli.py
aioboot/context.py
aioboot/ctx.py
aioboot/dependency.py
aioboot/di.py
aioboot/exceptions.py
aioboot/request.py
aioboot/response.py
aioboot/routing.py
aioboot/typedefs.py
aioboot-0.3.0.dist-info/METADATA
aioboot-0.3.0.dist-info/WHEEL
aioboot-0.3.0.dist-info/top_level.txt
aioboot-0.3.0.dist-info/RECORD
